arizon_usb_apiserver/Config.py
arizon_usb_apiserver/Parser.py
arizon_usb_apiserver/Sensor.py
arizon_usb_apiserver/__init__.py
arizon_usb_apiserver/__main__.py
arizon_usb_apiserver/apiserver/__init__.py
arizon_usb_apiserver/apiserver/app.py
arizon_usb_apiserver/apiserver/grpc_server.py
arizon_usb_apiserver/apiserver/main.py
arizon_usb_apiserver/apiserver/restful_server.py
arizon_usb_apiserver/apiserver/server.py
arizon_usb_apiserver/client/__init__.py
arizon_usb_apiserver/client/grpc/Client.py
arizon_usb_apiserver/client/grpc/__init__.py
arizon_usb_apiserver/client/restful/__init__.py
arizon_usb_apiserver/client/restful/client.py
arizon_usb_apiserver/client/restful/types.py
arizon_usb_apiserver/cmd/__init__.py
arizon_usb_apiserver/cmd/configure.py
arizon_usb_apiserver/cmd/test_grpc.py
arizon_usb_apiserver/cmd/test_restful.py
arizon_usb_apiserver/grpc/__init__.py
arizon_usb_apiserver/grpc/force_packet_pb2.py
arizon_usb_apiserver/grpc/force_packet_pb2_grpc.py
arizon_usb_apiserver-0.4.7.dist-info/METADATA
arizon_usb_apiserver-0.4.7.dist-info/WHEEL
arizon_usb_apiserver-0.4.7.dist-info/top_level.txt
arizon_usb_apiserver-0.4.7.dist-info/RECORD
