Metadata-Version: 2.1
Name: arizon-usb-apiserver
Version: 0.4.7
Summary: Driver for Arizona USB Pressure Sensor
Author: davidliyutong
Author-email: davidliyutong@sjtu.edu.cn
Requires-Python: >=3.7
Requires-Dist: pyserial
Requires-Dist: numpy
Requires-Dist: fastapi (>=0.87.0)
Requires-Dist: uvicorn (>=0.20.0)
Requires-Dist: pyyaml
Requires-Dist: py-cli-interaction
Requires-Dist: httpx
Requires-Dist: attr
Requires-Dist: grpcio
Requires-Dist: grpcio-tools
